lil_histie/__init__.py
lil_histie/histogram.py
lil_histie/__pycache__/__init__.cpython-37.pyc
lil_histie/__pycache__/histogram.cpython-37.pyc
lil_histie-0.0.1.dist-info/LICENSE.txt
lil_histie-0.0.1.dist-info/METADATA
lil_histie-0.0.1.dist-info/WHEEL
lil_histie-0.0.1.dist-info/entry_points.txt
lil_histie-0.0.1.dist-info/top_level.txt
lil_histie-0.0.1.dist-info/RECORD
