Metadata-Version: 2.1
Name: lil-histie
Version: 0.0.1
Summary: Simple CLI to display histograms from piped gdalinfo output.
Home-page: https://github.com/kovaca/lil-histie
Author: Alex Kovac
Author-email: akovac@wri.org
License: MIT
Platform: UNKNOWN
Classifier: Programming Language :: Python :: 3
Classifier: License :: OSI Approved :: MIT License
Classifier: Operating System :: OS Independent
Requires-Python: >=3.6
Requires-Dist: Click
